Metadata-Version: 1.1
Name: FYS2130-FreqAn
Version: 0.1.5
Summary: Basic package for frequency analysis in FYS2130.
Home-page: UNKNOWN
Author: Anton Brekke
Author-email: anton.a@hotmail.no
License: UNKNOWN
Platform: UNKNOWN
Classifier: 
